{
  "items": [
    {
      "kind": "youtube#searchResult",
      "etag": "3b0uAJv_I_QOfYbqUs7R4cryzLU",
      "id": {
        "kind": "youtube#video",
        "videoId": "ma67yOdMQfs"
      },
      "snippet": {
        "publishedAt": "2021-01-23T17:00:15Z",
        "channelId": "UC--3c8RqSfAqYBdDjIG3UNA",
        "title": "These Were The All-Time Surfing Moments Of The Year | Best Of 2020",
        "description": "Well, that was a weird ride. Though it hasn't been easy, at least when we fixed our gaze on the ocean — or favorite place in the ...",
        "thumbnails": {
          "default": {
            "url": "https://i.ytimg.com/vi/ma67yOdMQfs/default.jpg",
            "width": 120,
            "height": 90
          },
          "medium": {
            "url": "https://i.ytimg.com/vi/ma67yOdMQfs/mqdefault.jpg",
            "width": 320,
            "height": 180
          },
          "high": {
            "url": "https://i.ytimg.com/vi/ma67yOdMQfs/hqdefault.jpg",
            "width": 480,
            "height": 360
          }
        },
        "channelTitle": "Red Bull Surfing",
        "liveBroadcastContent": "none",
        "publishTime": "2021-01-23T17:00:15Z"
      }
    },
    {
      "kind": "youtube#searchResult",
      "etag": "2yOrRH6Aw8gGVmGetSQ_7SgQrNY",
      "id": {
        "kind": "youtube#video",
        "videoId": "hmjO9TUfQm4"
      },
      "snippet": {
        "publishedAt": "2022-02-25T00:52:56Z",
        "channelId": "UChuLeaTGRcfzo0UjL-2qSbQ",
        "title": "WATCH LIVE SLO CAL Open at Morro Bay Day 1",
        "description": "WSL Subscribe to the WSL for more action: https://goo.gl/VllRuj Watch all the latest surfing action of the world's best surfers in the ...",
        "thumbnails": {
          "default": {
            "url": "https://i.ytimg.com/vi/hmjO9TUfQm4/default.jpg",
            "width": 120,
            "height": 90
          },
          "medium": {
            "url": "https://i.ytimg.com/vi/hmjO9TUfQm4/mqdefault.jpg",
            "width": 320,
            "height": 180
          },
          "high": {
            "url": "https://i.ytimg.com/vi/hmjO9TUfQm4/hqdefault.jpg",
            "width": 480,
            "height": 360
          }
        },
        "channelTitle": "World Surf League",
        "liveBroadcastContent": "none",
        "publishTime": "2022-02-25T00:52:56Z"
      }
    },
    {
      "kind": "youtube#searchResult",
      "etag": "rNvWqF0tib6QpZnui_7HpNcvVkY",
      "id": {
        "kind": "youtube#video",
        "videoId": "rpMZEAdWVtE"
      },
      "snippet": {
        "publishedAt": "2022-02-24T11:01:44Z",
        "channelId": "UCVo06dBGK9VBBhq15wJxZHQ",
        "title": "🔵 (ASMR) Waves of the World/Surfing 24/7 Hawaii- With Relaxing Music 🌊",
        "description": "Waves of the World Filmers: Chris Kincade: https://www.instagram.com/chriskincade.wotw Andre Botha: ...",
        "thumbnails": {
          "default": {
            "url": "https://i.ytimg.com/vi/rpMZEAdWVtE/default_live.jpg",
            "width": 120,
            "height": 90
          },
          "medium": {
            "url": "https://i.ytimg.com/vi/rpMZEAdWVtE/mqdefault_live.jpg",
            "width": 320,
            "height": 180
          },
          "high": {
            "url": "https://i.ytimg.com/vi/rpMZEAdWVtE/hqdefault_live.jpg",
            "width": 480,
            "height": 360
          }
        },
        "channelTitle": "Chris Kincade Media - Waves of the World ",
        "liveBroadcastContent": "live",
        "publishTime": "2022-02-24T11:01:44Z"
      }
    },
    {
      "kind": "youtube#searchResult",
      "etag": "UXJu7iBAglaXaaAprKSvDBYoSYI",
      "id": {
        "kind": "youtube#video",
        "videoId": "s6eEzuY-mjA"
      },
      "snippet": {
        "publishedAt": "2022-02-22T20:00:32Z",
        "channelId": "UC--3c8RqSfAqYBdDjIG3UNA",
        "title": "Race &amp; Surfing: A Brief History With Selema Masekela | IN PLAIN SIGHT",
        "description": "Surfing's history – from Africa to Polynesia to the Americas – is one that's rich, diverse, and incredibly nuanced. So much so, that ...",
        "thumbnails": {
          "default": {
            "url": "https://i.ytimg.com/vi/s6eEzuY-mjA/default.jpg",
            "width": 120,
            "height": 90
          },
          "medium": {
            "url": "https://i.ytimg.com/vi/s6eEzuY-mjA/mqdefault.jpg",
            "width": 320,
            "height": 180
          },
          "high": {
            "url": "https://i.ytimg.com/vi/s6eEzuY-mjA/hqdefault.jpg",
            "width": 480,
            "height": 360
          }
        },
        "channelTitle": "Red Bull Surfing",
        "liveBroadcastContent": "none",
        "publishTime": "2022-02-22T20:00:32Z"
      }
    },
    {
      "kind": "youtube#searchResult",
      "etag": "OyaQ1-zx79L82JgduPiynfB25v8",
      "id": {
        "kind": "youtube#video",
        "videoId": "d5PW_74ujUs"
      },
      "snippet": {
        "publishedAt": "2022-02-21T23:36:02Z",
        "channelId": "UCVo06dBGK9VBBhq15wJxZHQ",
        "title": "4k UNEDITED CARNAGE AT PIPELINE - 2022 SURFING - THE BIGGEST DAYS☑️",
        "description": "4K unedited carnage at Banzai Pipeline. All filmed in 2022 by Justin Mack https://www.instagram.com/jmack808 Waves of the ...",
        "thumbnails": {
          "default": {
            "url": "https://i.ytimg.com/vi/d5PW_74ujUs/default.jpg",
            "width": 120,
            "height": 90
          },
          "medium": {
            "url": "https://i.ytimg.com/vi/d5PW_74ujUs/mqdefault.jpg",
            "width": 320,
            "height": 180
          },
          "high": {
            "url": "https://i.ytimg.com/vi/d5PW_74ujUs/hqdefault.jpg",
            "width": 480,
            "height": 360
          }
        },
        "channelTitle": "Chris Kincade Media - Waves of the World ",
        "liveBroadcastContent": "none",
        "publishTime": "2022-02-21T23:36:02Z"
      }
    },
    {
      "kind": "youtube#searchResult",
      "etag": "O5KYGbK80nzWpgcpqu34KwBjgPM",
      "id": {
        "kind": "youtube#video",
        "videoId": "DDOzbNjODm4"
      },
      "snippet": {
        "publishedAt": "2022-02-24T11:46:56Z",
        "channelId": "UCFdhu2ZZ7GBbGliV8tZ0UJw",
        "title": "POV SURF - HEAVEN MOOD",
        "description": "POV Surfing with incredibles colors and beautiful waves. We had those colors because of the gaz in the sky due to the Tonga ...",
        "thumbnails": {
          "default": {
            "url": "https://i.ytimg.com/vi/DDOzbNjODm4/default.jpg",
            "width": 120,
            "height": 90
          },
          "medium": {
            "url": "https://i.ytimg.com/vi/DDOzbNjODm4/mqdefault.jpg",
            "width": 320,
            "height": 180
          },
          "high": {
            "url": "https://i.ytimg.com/vi/DDOzbNjODm4/hqdefault.jpg",
            "width": 480,
            "height": 360
          }
        },
        "channelTitle": "Kai Noa",
        "liveBroadcastContent": "none",
        "publishTime": "2022-02-24T11:46:56Z"
      }
    },
    {
      "kind": "youtube#searchResult",
      "etag": "R6P4b-mwD0kX13S8Z8PBxc8I2y8",
      "id": {
        "kind": "youtube#video",
        "videoId": "CAQkaPwhT-E"
      },
      "snippet": {
        "publishedAt": "2022-02-24T08:01:53Z",
        "channelId": "UC8pmG8IGaDyDTc6xBJiyXBQ",
        "title": "King Of The Rock , Your Decision ? - The Edit - Snapper Surfing Australia",
        "description": "King of the rock , the edit from our other channel without the music for all you natural ocean sound lovers ....:) Snapper Rocks ...",
        "thumbnails": {
          "default": {
            "url": "https://i.ytimg.com/vi/CAQkaPwhT-E/default.jpg",
            "width": 120,
            "height": 90
          },
          "medium": {
            "url": "https://i.ytimg.com/vi/CAQkaPwhT-E/mqdefault.jpg",
            "width": 320,
            "height": 180
          },
          "high": {
            "url": "https://i.ytimg.com/vi/CAQkaPwhT-E/hqdefault.jpg",
            "width": 480,
            "height": 360
          }
        },
        "channelTitle": "Surf Today ",
        "liveBroadcastContent": "none",
        "publishTime": "2022-02-24T08:01:53Z"
      }
    },
    {
      "kind": "youtube#searchResult",
      "etag": "5e_4VyKSKxS4h4CGzWmOTd_dc80",
      "id": {
        "kind": "youtube#video",
        "videoId": "HB2jZut-Wnc"
      },
      "snippet": {
        "publishedAt": "2022-01-24T05:28:15Z",
        "channelId": "UCVo06dBGK9VBBhq15wJxZHQ",
        "title": "🔴4k Pipeline Surf - 1/21/22 - Does it Get Much Better Then This??🆕",
        "description": "Filmed at Banzai Pipeline, Oahu on January 21st, 2022 by Andy Potts and Jr Maosi Let me know what you thought of today's ...",
        "thumbnails": {
          "default": {
            "url": "https://i.ytimg.com/vi/HB2jZut-Wnc/default.jpg",
            "width": 120,
            "height": 90
          },
          "medium": {
            "url": "https://i.ytimg.com/vi/HB2jZut-Wnc/mqdefault.jpg",
            "width": 320,
            "height": 180
          },
          "high": {
            "url": "https://i.ytimg.com/vi/HB2jZut-Wnc/hqdefault.jpg",
            "width": 480,
            "height": 360
          }
        },
        "channelTitle": "Chris Kincade Media - Waves of the World ",
        "liveBroadcastContent": "none",
        "publishTime": "2022-01-24T05:28:15Z"
      }
    },
    {
      "kind": "youtube#searchResult",
      "etag": "26wn8Kd11U_1drHfA3nBHB2T43E",
      "id": {
        "kind": "youtube#video",
        "videoId": "ar1TkD5Cz_o"
      },
      "snippet": {
        "publishedAt": "2019-01-16T15:00:02Z",
        "channelId": "UC--3c8RqSfAqYBdDjIG3UNA",
        "title": "One Last Look At The Best Surf Videos Of 2018",
        "description": "Join us for a final look at one of the most exciting years in surfing. 2018 was packed with epic moments in surfing, from Indonesia ...",
        "thumbnails": {
          "default": {
            "url": "https://i.ytimg.com/vi/ar1TkD5Cz_o/default.jpg",
            "width": 120,
            "height": 90
          },
          "medium": {
            "url": "https://i.ytimg.com/vi/ar1TkD5Cz_o/mqdefault.jpg",
            "width": 320,
            "height": 180
          },
          "high": {
            "url": "https://i.ytimg.com/vi/ar1TkD5Cz_o/hqdefault.jpg",
            "width": 480,
            "height": 360
          }
        },
        "channelTitle": "Red Bull Surfing",
        "liveBroadcastContent": "none",
        "publishTime": "2019-01-16T15:00:02Z"
      }
    },
    {
      "kind": "youtube#searchResult",
      "etag": "C6_W6Cdom3Z8cX8qugHe0nV-MeI",
      "id": {
        "kind": "youtube#video",
        "videoId": "W7h-Yho8EB0"
      },
      "snippet": {
        "publishedAt": "2019-06-15T15:21:45Z",
        "channelId": "UCqhnX4jA0A5paNd1v-zEysw",
        "title": "GoPro: Top 10 Surf Moments",
        "description": "Celebrate International Surf Day with GoPro's Top 10 Surf Moments. Shot 100% on GoPro: http://bit.ly/2wUMwfI Get stoked and ...",
        "thumbnails": {
          "default": {
            "url": "https://i.ytimg.com/vi/W7h-Yho8EB0/default.jpg",
            "width": 120,
            "height": 90
          },
          "medium": {
            "url": "https://i.ytimg.com/vi/W7h-Yho8EB0/mqdefault.jpg",
            "width": 320,
            "height": 180
          },
          "high": {
            "url": "https://i.ytimg.com/vi/W7h-Yho8EB0/hqdefault.jpg",
            "width": 480,
            "height": 360
          }
        },
        "channelTitle": "GoPro",
        "liveBroadcastContent": "none",
        "publishTime": "2019-06-15T15:21:45Z"
      }
    },
    {
      "kind": "youtube#searchResult",
      "etag": "n5vWKsEZS2hfYfPqOMk_DnZ4MDI",
      "id": {
        "kind": "youtube#video",
        "videoId": "Smgql_DESn8"
      },
      "snippet": {
        "publishedAt": "2021-09-15T10:59:56Z",
        "channelId": "UC9rMiEjNaCSsebs31MRDCRA",
        "title": "Stray Kids &quot;Surfin&#39; (리노, 창빈, 필릭스)&quot; Video",
        "description": "Stray Kids(스트레이 키즈) \"Surfin' (리노, 창빈, 필릭스)\" Video Stray Kids THE 2ND ALBUM \"NOEASY\" iTunes & Apple Music: ...",
        "thumbnails": {
          "default": {
            "url": "https://i.ytimg.com/vi/Smgql_DESn8/default.jpg",
            "width": 120,
            "height": 90
          },
          "medium": {
            "url": "https://i.ytimg.com/vi/Smgql_DESn8/mqdefault.jpg",
            "width": 320,
            "height": 180
          },
          "high": {
            "url": "https://i.ytimg.com/vi/Smgql_DESn8/hqdefault.jpg",
            "width": 480,
            "height": 360
          }
        },
        "channelTitle": "Stray Kids",
        "liveBroadcastContent": "none",
        "publishTime": "2021-09-15T10:59:56Z"
      }
    },
    {
      "kind": "youtube#searchResult",
      "etag": "NPvms4v3yf7o9Za34ft5mfQcl9s",
      "id": {
        "kind": "youtube#video",
        "videoId": "rj7xMBxd5iY"
      },
      "snippet": {
        "publishedAt": "2017-11-12T11:09:52Z",
        "channelId": "UCiiFGfvlKvX3uzMovO3unaw",
        "title": "BIG WAVE SURFING COMPILATION 2017",
        "description": "BIG WAVE SURFING COMPILATION 2017 ** REVISED **AMAZING FOOTAGE ** WITH 60-100FT- HUGE SURF Please ...",
        "thumbnails": {
          "default": {
            "url": "https://i.ytimg.com/vi/rj7xMBxd5iY/default.jpg",
            "width": 120,
            "height": 90
          },
          "medium": {
            "url": "https://i.ytimg.com/vi/rj7xMBxd5iY/mqdefault.jpg",
            "width": 320,
            "height": 180
          },
          "high": {
            "url": "https://i.ytimg.com/vi/rj7xMBxd5iY/hqdefault.jpg",
            "width": 480,
            "height": 360
          }
        },
        "channelTitle": "Absolutely Flawless",
        "liveBroadcastContent": "none",
        "publishTime": "2017-11-12T11:09:52Z"
      }
    },
    {
      "kind": "youtube#searchResult",
      "etag": "cI3q23StEbKZMjzpasfuzen378g",
      "id": {
        "kind": "youtube#video",
        "videoId": "dleyTAkUIyw"
      },
      "snippet": {
        "publishedAt": "2022-02-24T19:31:37Z",
        "channelId": "UC4qa5EroJxnQM6Sng9WhgsQ",
        "title": "We Made it to Paradise!! (Hawaii)",
        "description": "Hawaii is firing! Well, compared to usual I guess it's not completely firing, but for me it's completely going off & I'll probably be ...",
        "thumbnails": {
          "default": {
            "url": "https://i.ytimg.com/vi/dleyTAkUIyw/default.jpg",
            "width": 120,
            "height": 90
          },
          "medium": {
            "url": "https://i.ytimg.com/vi/dleyTAkUIyw/mqdefault.jpg",
            "width": 320,
            "height": 180
          },
          "high": {
            "url": "https://i.ytimg.com/vi/dleyTAkUIyw/hqdefault.jpg",
            "width": 480,
            "height": 360
          }
        },
        "channelTitle": "Ben Gravy",
        "liveBroadcastContent": "none",
        "publishTime": "2022-02-24T19:31:37Z"
      }
    },
    {
      "kind": "youtube#searchResult",
      "etag": "6xEZ86y9U8hQhVsZ4iod2U0gVH0",
      "id": {
        "kind": "youtube#video",
        "videoId": "sONWgVmQOLE"
      },
      "snippet": {
        "publishedAt": "2022-02-25T09:39:26Z",
        "channelId": "UChuLeaTGRcfzo0UjL-2qSbQ",
        "title": "C A R V E Great Lakes Pro QS1000 - Final Day",
        "description": "LIVE :: Watch the first event of the 2022 VISSLA NSW Pro Surf Series, the Carve Australia Great Lakes Pro QS1000 day 3 LIVE ...",
        "thumbnails": {
          "default": {
            "url": "https://i.ytimg.com/vi/sONWgVmQOLE/default.jpg",
            "width": 120,
            "height": 90
          },
          "medium": {
            "url": "https://i.ytimg.com/vi/sONWgVmQOLE/mqdefault.jpg",
            "width": 320,
            "height": 180
          },
          "high": {
            "url": "https://i.ytimg.com/vi/sONWgVmQOLE/hqdefault.jpg",
            "width": 480,
            "height": 360
          }
        },
        "channelTitle": "World Surf League",
        "liveBroadcastContent": "none",
        "publishTime": "2022-02-25T09:39:26Z"
      }
    },
    {
      "kind": "youtube#searchResult",
      "etag": "ZvkmpHaxVskA3fHchR3aJ00eGl8",
      "id": {
        "kind": "youtube#video",
        "videoId": "PwSZ_O5zQuU"
      },
      "snippet": {
        "publishedAt": "2022-02-25T03:00:12Z",
        "channelId": "UC8z5r8UM4DBjCwkHMlu6j0Q",
        "title": "Surfing Pipeline Requires FULL COMMITMENT",
        "description": "TIMESTAMPS: 0:00 Cody Young 0:08 Unidentified 0:38 Cesar Petroni 0:56 Unidentified 1:28 Al Cleland Jr. 2:04 Reef McIntosh ...",
        "thumbnails": {
          "default": {
            "url": "https://i.ytimg.com/vi/PwSZ_O5zQuU/default.jpg",
            "width": 120,
            "height": 90
          },
          "medium": {
            "url": "https://i.ytimg.com/vi/PwSZ_O5zQuU/mqdefault.jpg",
            "width": 320,
            "height": 180
          },
          "high": {
            "url": "https://i.ytimg.com/vi/PwSZ_O5zQuU/hqdefault.jpg",
            "width": 480,
            "height": 360
          }
        },
        "channelTitle": "Off Da Lip",
        "liveBroadcastContent": "none",
        "publishTime": "2022-02-25T03:00:12Z"
      }
    },
    {
      "kind": "youtube#searchResult",
      "etag": "DM_sYVlkO3YXLDW99XOokPHzxx0",
      "id": {
        "kind": "youtube#video",
        "videoId": "LUdqckbhzwY"
      },
      "snippet": {
        "publishedAt": "2021-09-13T21:53:44Z",
        "channelId": "UCsG5dkqFUHZO6eY9uOzQqow",
        "title": "A 100% Authentic New Zealand Surf Film | &#39;Bro Town&#39;",
        "description": "When it comes to New Zealand, local boys Elliot Paerata Reid, Kehu Butler, Ware Wano, and Dune Kennings know exactly when ...",
        "thumbnails": {
          "default": {
            "url": "https://i.ytimg.com/vi/LUdqckbhzwY/default.jpg",
            "width": 120,
            "height": 90
          },
          "medium": {
            "url": "https://i.ytimg.com/vi/LUdqckbhzwY/mqdefault.jpg",
            "width": 320,
            "height": 180
          },
          "high": {
            "url": "https://i.ytimg.com/vi/LUdqckbhzwY/hqdefault.jpg",
            "width": 480,
            "height": 360
          }
        },
        "channelTitle": "Stab: We like to surf",
        "liveBroadcastContent": "none",
        "publishTime": "2021-09-13T21:53:44Z"
      }
    },
    {
      "kind": "youtube#searchResult",
      "etag": "I7oeGi0iCuI-0igdRRQO3qGhq8o",
      "id": {
        "kind": "youtube#video",
        "videoId": "S0IWzE-mzWM"
      },
      "snippet": {
        "publishedAt": "2022-02-11T15:00:13Z",
        "channelId": "UCeYue9Nbodzg3T1Nt88E3fg",
        "title": "Surfing In Paradise",
        "description": "Mason Ho and Sheldon Paishon surf a mystical day here in paradise. Then the boys get a surprise FaceTime from Mick Fanning ...",
        "thumbnails": {
          "default": {
            "url": "https://i.ytimg.com/vi/S0IWzE-mzWM/default.jpg",
            "width": 120,
            "height": 90
          },
          "medium": {
            "url": "https://i.ytimg.com/vi/S0IWzE-mzWM/mqdefault.jpg",
            "width": 320,
            "height": 180
          },
          "high": {
            "url": "https://i.ytimg.com/vi/S0IWzE-mzWM/hqdefault.jpg",
            "width": 480,
            "height": 360
          }
        },
        "channelTitle": "Ho & Pringle Productions",
        "liveBroadcastContent": "none",
        "publishTime": "2022-02-11T15:00:13Z"
      }
    },
    {
      "kind": "youtube#searchResult",
      "etag": "-5LxO5qQ18VwY0bDFT0jqGDBQws",
      "id": {
        "kind": "youtube#video",
        "videoId": "mRHG2lWvF4A"
      },
      "snippet": {
        "publishedAt": "2022-01-24T19:00:27Z",
        "channelId": "UCo_q6aOlvPH7M-j_XGWVgXg",
        "title": "THE MOST CROWDED PIPELINE EVER! (ITS GETTING WORSE)",
        "description": "STAY PSYCHED MERCHANDISE: https://www.jamieobrienshop.com - JAMIE O'BRIEN SURF SCHOOL TURTLE BAY HAWAII ...",
        "thumbnails": {
          "default": {
            "url": "https://i.ytimg.com/vi/mRHG2lWvF4A/default.jpg",
            "width": 120,
            "height": 90
          },
          "medium": {
            "url": "https://i.ytimg.com/vi/mRHG2lWvF4A/mqdefault.jpg",
            "width": 320,
            "height": 180
          },
          "high": {
            "url": "https://i.ytimg.com/vi/mRHG2lWvF4A/hqdefault.jpg",
            "width": 480,
            "height": 360
          }
        },
        "channelTitle": "Jamie O'Brien",
        "liveBroadcastContent": "none",
        "publishTime": "2022-01-24T19:00:27Z"
      }
    },
    {
      "kind": "youtube#searchResult",
      "etag": "syDwCl98w9kUewTd4MOg8XNmrZM",
      "id": {
        "kind": "youtube#video",
        "videoId": "nIAhZMWlAzc"
      },
      "snippet": {
        "publishedAt": "2022-02-23T11:00:22Z",
        "channelId": "UCzcQOTuXYGuCvTekySb_CeQ",
        "title": "Storm Surfing - Keramas",
        "description": "We've had some wild weather over the last few days here in Bali. Strong winds and heavy rain kept most people inside, but since ...",
        "thumbnails": {
          "default": {
            "url": "https://i.ytimg.com/vi/nIAhZMWlAzc/default.jpg",
            "width": 120,
            "height": 90
          },
          "medium": {
            "url": "https://i.ytimg.com/vi/nIAhZMWlAzc/mqdefault.jpg",
            "width": 320,
            "height": 180
          },
          "high": {
            "url": "https://i.ytimg.com/vi/nIAhZMWlAzc/hqdefault.jpg",
            "width": 480,
            "height": 360
          }
        },
        "channelTitle": "Surfers of Bali",
        "liveBroadcastContent": "none",
        "publishTime": "2022-02-23T11:00:22Z"
      }
    },
    {
      "kind": "youtube#searchResult",
      "etag": "UfQ5mQiaRYS-yCgpfh17RKcW7MY",
      "id": {
        "kind": "youtube#video",
        "videoId": "W-sz0muRr9M"
      },
      "snippet": {
        "publishedAt": "2022-02-18T19:51:41Z",
        "channelId": "UCf5CA0OsvhhU-6AcSjT1oKQ",
        "title": "The novelty BOOG Slab wave and SKETCHY River break !!! (RAW Bonus Footage)",
        "description": "Chasing weird novelty slab waves with Blair Conklin and crazy river break that gets too crazy to surf! Plus crazy finless surf action ...",
        "thumbnails": {
          "default": {
            "url": "https://i.ytimg.com/vi/W-sz0muRr9M/default.jpg",
            "width": 120,
            "height": 90
          },
          "medium": {
            "url": "https://i.ytimg.com/vi/W-sz0muRr9M/mqdefault.jpg",
            "width": 320,
            "height": 180
          },
          "high": {
            "url": "https://i.ytimg.com/vi/W-sz0muRr9M/hqdefault.jpg",
            "width": 480,
            "height": 360
          }
        },
        "channelTitle": "BEEFS T.V.",
        "liveBroadcastContent": "none",
        "publishTime": "2022-02-18T19:51:41Z"
      }
    },
    {
      "kind": "youtube#searchResult",
      "etag": "uhzDGhpt8qD_211ARIBzA7EPsH0",
      "id": {
        "kind": "youtube#video",
        "videoId": "Pc1oO6xeJXM"
      },
      "snippet": {
        "publishedAt": "2022-02-22T18:00:10Z",
        "channelId": "UCm9NnEJTi7_B86QWgQiUCJA",
        "title": "I BEAT KELLY SLATER ... (ALMOST)",
        "description": "Koa Smith gets a last minute wild card entry to the Hurley Sunset Pro@World Surf League CT event. Koa gets matched up against ...",
        "thumbnails": {
          "default": {
            "url": "https://i.ytimg.com/vi/Pc1oO6xeJXM/default.jpg",
            "width": 120,
            "height": 90
          },
          "medium": {
            "url": "https://i.ytimg.com/vi/Pc1oO6xeJXM/mqdefault.jpg",
            "width": 320,
            "height": 180
          },
          "high": {
            "url": "https://i.ytimg.com/vi/Pc1oO6xeJXM/hqdefault.jpg",
            "width": 480,
            "height": 360
          }
        },
        "channelTitle": "The Smith Brothers",
        "liveBroadcastContent": "none",
        "publishTime": "2022-02-22T18:00:10Z"
      }
    },
    {
      "kind": "youtube#searchResult",
      "etag": "vMpgOGf3_0zX45RjfLNkdDljUuk",
      "id": {
        "kind": "youtube#video",
        "videoId": "6GUtd7f1_Xo"
      },
      "snippet": {
        "publishedAt": "2019-01-01T20:01:55Z",
        "channelId": "UCVk7uRN7g-q_uHMaAjHxk8A",
        "title": "THE GIRLS OF SURFING XIX",
        "description": "The Girls of Surfing 2018 edition Join the page here : https://www.facebook.com/thegirlsofsurfing/ Instagram @jolieoligny Twitter ...",
        "thumbnails": {
          "default": {
            "url": "https://i.ytimg.com/vi/6GUtd7f1_Xo/default.jpg",
            "width": 120,
            "height": 90
          },
          "medium": {
            "url": "https://i.ytimg.com/vi/6GUtd7f1_Xo/mqdefault.jpg",
            "width": 320,
            "height": 180
          },
          "high": {
            "url": "https://i.ytimg.com/vi/6GUtd7f1_Xo/hqdefault.jpg",
            "width": 480,
            "height": 360
          }
        },
        "channelTitle": "thegirlsofsurfing",
        "liveBroadcastContent": "none",
        "publishTime": "2019-01-01T20:01:55Z"
      }
    },
    {
      "kind": "youtube#searchResult",
      "etag": "luPhmaaEnrOyNYuEwkz8bTH7IJ8",
      "id": {
        "kind": "youtube#video",
        "videoId": "EBMYj8qgCWA"
      },
      "snippet": {
        "publishedAt": "2022-02-22T22:50:16Z",
        "channelId": "UCfNAMNoNxYWk-CccrE3Qkaw",
        "title": "FUN DAY OF SURFING ON OAHU WITH ALANA AND JACK",
        "description": "Don't forget to subscribe!! Thanks for watching!! Filmed and edit Jake Zielinski.",
        "thumbnails": {
          "default": {
            "url": "https://i.ytimg.com/vi/EBMYj8qgCWA/default.jpg",
            "width": 120,
            "height": 90
          },
          "medium": {
            "url": "https://i.ytimg.com/vi/EBMYj8qgCWA/mqdefault.jpg",
            "width": 320,
            "height": 180
          },
          "high": {
            "url": "https://i.ytimg.com/vi/EBMYj8qgCWA/hqdefault.jpg",
            "width": 480,
            "height": 360
          }
        },
        "channelTitle": "Alana Blanchard and Jack Freestone",
        "liveBroadcastContent": "none",
        "publishTime": "2022-02-22T22:50:16Z"
      }
    },
    {
      "kind": "youtube#searchResult",
      "etag": "w9s0yxL2jRxirDDLgL6x3-bzvlk",
      "id": {
        "kind": "youtube#video",
        "videoId": "JyY9aRNo3RM"
      },
      "snippet": {
        "publishedAt": "2022-02-21T09:15:57Z",
        "channelId": "UCe_ZLwzh-73vuzoZesJJgkw",
        "title": "Go Hard Or Go Home Surfing By Dane Reynolds.",
        "description": "In this video we break down the surfing of Dane Reynolds. . . . . . If you want to improve your surfing make sure you check out the ...",
        "thumbnails": {
          "default": {
            "url": "https://i.ytimg.com/vi/JyY9aRNo3RM/default.jpg",
            "width": 120,
            "height": 90
          },
          "medium": {
            "url": "https://i.ytimg.com/vi/JyY9aRNo3RM/mqdefault.jpg",
            "width": 320,
            "height": 180
          },
          "high": {
            "url": "https://i.ytimg.com/vi/JyY9aRNo3RM/hqdefault.jpg",
            "width": 480,
            "height": 360
          }
        },
        "channelTitle": "Ombe Surf",
        "liveBroadcastContent": "none",
        "publishTime": "2022-02-21T09:15:57Z"
      }
    },
    {
      "kind": "youtube#searchResult",
      "etag": "RlDuv-YJj0xwDjW2RJCKBEEcROw",
      "id": {
        "kind": "youtube#video",
        "videoId": "EDViMzH84_o"
      },
      "snippet": {
        "publishedAt": "2022-02-06T02:36:24Z",
        "channelId": "UChuLeaTGRcfzo0UjL-2qSbQ",
        "title": "Kelly Slater vs Seth Moniz FINAL - FULL HEAT REPLAY Billabong Pro Pipeline",
        "description": "Full heat replay of the Final featuring Kelly Slater vs Seth Moniz - Billabong Pro Pipeline. As the epicenter of the surf universe and ...",
        "thumbnails": {
          "default": {
            "url": "https://i.ytimg.com/vi/EDViMzH84_o/default.jpg",
            "width": 120,
            "height": 90
          },
          "medium": {
            "url": "https://i.ytimg.com/vi/EDViMzH84_o/mqdefault.jpg",
            "width": 320,
            "height": 180
          },
          "high": {
            "url": "https://i.ytimg.com/vi/EDViMzH84_o/hqdefault.jpg",
            "width": 480,
            "height": 360
          }
        },
        "channelTitle": "World Surf League",
        "liveBroadcastContent": "none",
        "publishTime": "2022-02-06T02:36:24Z"
      }
    }
  ]
}
